./.gitignore
./LICENSE
./MANIFEST.in
./PKG-INFO
./README.md
./loader.py
./pyproject.toml
./server.py
./update_schemas.py
./uv.lock
./version_manager.py
./osim-schema/CHANGELOG.md
./osim-schema/CODE_OF_CONDUCT.md
./osim-schema/CONTRIBUTING.md
./osim-schema/LICENSE
./osim-schema/README.md
./osim-schema/RULL_REQUEST_TEMPLATE.md
./osim-schema/dictionaries.json
./osim-schema/valid.json
./osim-schema/version.json
./osim-schema/examples/README.md
./osim-schema/examples/alert/anomalous_behavior/abnormal_behavior_access_anomaly.json
./osim-schema/examples/alert/anomalous_behavior/abnormal_behavior_host_abnormality.json
./osim-schema/examples/alert/anomalous_behavior/abnormal_behavior_traffic_anomaly.json
./osim-schema/examples/alert/data_security/data_security_data_leak.json
./osim-schema/examples/alert/data_security/data_security_tampering.json
./osim-schema/examples/alert/malware/malware_botnet.json
./osim-schema/examples/alert/malware/malware_computer_virus.json
./osim-schema/examples/alert/malware/malware_embedded_webpage.json
./osim-schema/examples/alert/malware/malware_mining.json
./osim-schema/examples/alert/malware/malware_network_worm.json
./osim-schema/examples/alert/malware/malware_ransomware.json
./osim-schema/examples/alert/malware/malware_trojan.json
./osim-schema/examples/alert/network_attack/network_attack_backdoor_exploit.json
./osim-schema/examples/alert/network_attack/network_attack_credential_attack.json
./osim-schema/examples/alert/network_attack/network_attack_dos.json
./osim-schema/examples/alert/network_attack/network_attack_email_threat.json
./osim-schema/examples/alert/network_attack/network_attack_host_exploit.json
./osim-schema/examples/alert/network_attack/network_attack_phishing.json
./osim-schema/examples/alert/network_attack/network_attack_scan_probe.json
./osim-schema/examples/alert/network_attack/network_attack_web.json
./osim-schema/examples/alert/network_attack/network_attack_web_tampering.json
osim_mcp_server-1.0.7.dist-info/METADATA
osim_mcp_server-1.0.7.dist-info/WHEEL
osim_mcp_server-1.0.7.dist-info/entry_points.txt
osim_mcp_server-1.0.7.dist-info/licenses/LICENSE
osim_mcp_server-1.0.7.dist-info/RECORD
